[1,["c4H9/7kGFIW64lwU9i8zkF","1b7940d9a"],["spriteFrame","_textureSetter"],["cc.SpriteFrame",["cc.LabelAtlas",["_name","fontSize","_fntConfig"],0]],[[1,0,1,2,4]],[[[[0,"numFont",23.76,{"commonHeight":27,"fontSize":23,"atlasName":"num0","fontDefDictionary":{"48":{"xOffset":0,"yOffset":0,"xAdvance":23,"rect":{"x":0,"y":0,"width":23,"height":27}},"49":{"xOffset":0,"yOffset":0,"xAdvance":23,"rect":{"x":23,"y":0,"width":23,"height":27}},"50":{"xOffset":0,"yOffset":0,"xAdvance":23,"rect":{"x":46,"y":0,"width":23,"height":27}},"51":{"xOffset":0,"yOffset":0,"xAdvance":23,"rect":{"x":69,"y":0,"width":23,"height":27}},"52":{"xOffset":0,"yOffset":0,"xAdvance":23,"rect":{"x":92,"y":0,"width":23,"height":27}},"53":{"xOffset":0,"yOffset":0,"xAdvance":23,"rect":{"x":115,"y":0,"width":23,"height":27}},"54":{"xOffset":0,"yOffset":0,"xAdvance":23,"rect":{"x":138,"y":0,"width":23,"height":27}},"55":{"xOffset":0,"yOffset":0,"xAdvance":23,"rect":{"x":161,"y":0,"width":23,"height":27}},"56":{"xOffset":0,"yOffset":0,"xAdvance":23,"rect":{"x":184,"y":0,"width":23,"height":27}},"57":{"xOffset":0,"yOffset":0,"xAdvance":23,"rect":{"x":207,"y":0,"width":23,"height":27}}},"kerningDict":{}}]],0,0,[0],[0],[0]],[[{"name":"num0","rect":[429,1756,228,27],"offset":[0,0],"originalSize":[230,27],"rotated":1,"capInsets":[0,0,0,0]}],[0],0,[0],[1],[1]]]]